src/.env
src/__init__.py
src/email_process.py
src/main.py
src/register.py
src/trx_process.py
trx_reader_demo-0.1.2.dist-info/WHEEL
trx_reader_demo-0.1.2.dist-info/METADATA
trx_reader_demo-0.1.2.dist-info/RECORD
