Metadata-Version: 2.1
Name: trx-reader-demo
Version: 0.1.2
Summary: This app reads a .csv file that contains trx information, send a formatted email with this content and load the information into a Mongodb cluster
Author: Romina Bareiro
Author-email: 100946603+RomiBareiro@users.noreply.github.com
Requires-Python: >=3.8,<4.0
Classifier: Programming Language :: Python :: 3
Classifier: Programming Language :: Python :: 3.8
Classifier: Programming Language :: Python :: 3.9
Classifier: Programming Language :: Python :: 3.10
